jupyter_chat_widget/__init__.py
jupyter_chat_widget/_version.py
jupyter_chat_widget/chat.py
jupyter_chat_widget/py.typed
jupyter_chat_widget-0.4.0.dist-info/METADATA
jupyter_chat_widget-0.4.0.dist-info/WHEEL
jupyter_chat_widget-0.4.0.dist-info/licenses/LICENSE
jupyter_chat_widget-0.4.0.dist-info/RECORD
