Metadata-Version: 2.4
Name: jupyter-chat-widget
Version: 0.4.0
Summary: A simple chat UI widget for Jupyter notebooks
Project-URL: Homepage, https://github.com/zansara/jupyter-chat-widget
Project-URL: Documentation, https://github.com/zansara/jupyter-chat-widget#readme
Project-URL: Repository, https://github.com/zansara/jupyter-chat-widget
Project-URL: Issues, https://github.com/zansara/jupyter-chat-widget/issues
Author-email: github@zansara.dev
License-Expression: MIT
License-File: LICENSE
Keywords: chat,ipywidgets,jupyter,llm,notebook,ui
Classifier: Development Status :: 3 - Alpha
Classifier: Framework :: Jupyter
Classifier: Intended Audience :: Developers
Classifier: License :: OSI Approved :: MIT License
Classifier: Operating System :: OS Independent
Classifier: Programming Language :: Python :: 3
Classifier: Programming Language :: Python :: 3.9
Classifier: Programming Language :: Python :: 3.10
Classifier: Programming Language :: Python :: 3.11
Classifier: Programming Language :: Python :: 3.12
Classifier: Programming Language :: Python :: 3.13
Requires-Python: >=3.9
Requires-Dist: ipywidgets<8.0.0
Provides-Extra: dev
Requires-Dist: build>=1.0; extra == 'dev'
Requires-Dist: pre-commit>=3.0; extra == 'dev'
Requires-Dist: pytest-cov>=4.0; extra == 'dev'
Requires-Dist: pytest>=7.0; extra == 'dev'
Requires-Dist: ruff>=0.4.0; extra == 'dev'
Provides-Extra: test
Requires-Dist: pytest-cov>=4.0; extra == 'test'
Requires-Dist: pytest>=7.0; extra == 'test'
